pywinauto/__init__.py
pywinauto/actionlogger.py
pywinauto/application.py
pywinauto/backend.py
pywinauto/base_wrapper.py
pywinauto/clipboard.py
pywinauto/controlproperties.py
pywinauto/element_info.py
pywinauto/findbestmatch.py
pywinauto/findwindows.py
pywinauto/fuzzydict.py
pywinauto/handleprops.py
pywinauto/keyboard.py
pywinauto/mouse.py
pywinauto/remote_memory_block.py
pywinauto/sysinfo.py
pywinauto/taskbar.py
pywinauto/timings.py
pywinauto/uia_defines.py
pywinauto/uia_element_info.py
pywinauto/win32_element_info.py
pywinauto/win32_hooks.py
pywinauto/win32defines.py
pywinauto/win32functions.py
pywinauto/win32structures.py
pywinauto/xml_helpers.py
pywinauto/controls/__init__.py
pywinauto/controls/common_controls.py
pywinauto/controls/hwndwrapper.py
pywinauto/controls/menuwrapper.py
pywinauto/controls/uia_controls.py
pywinauto/controls/uiawrapper.py
pywinauto/controls/win32_controls.py
pywinauto/linux/__init__.py
pywinauto/linux/clipboard.py
pywinauto/linux/keyboard.py
pywinauto/tests/__init__.py
pywinauto/tests/_menux.py
pywinauto/tests/allcontrols.py
pywinauto/tests/asianhotkey.py
pywinauto/tests/comboboxdroppedheight.py
pywinauto/tests/comparetoreffont.py
pywinauto/tests/leadtrailspaces.py
pywinauto/tests/miscvalues.py
pywinauto/tests/missalignment.py
pywinauto/tests/missingextrastring.py
pywinauto/tests/overlapping.py
pywinauto/tests/repeatedhotkey.py
pywinauto/tests/translation.py
pywinauto/tests/truncation.py
pywinauto-0.6.7.dist-info/LICENSE
pywinauto-0.6.7.dist-info/METADATA
pywinauto-0.6.7.dist-info/WHEEL
pywinauto-0.6.7.dist-info/top_level.txt
pywinauto-0.6.7.dist-info/RECORD
