Metadata-Version: 1.1
Name: pywinauto
Version: 0.6.7
Summary: A set of Python modules to automate the Microsoft Windows GUI
Home-page: http://pywinauto.github.io/
Author: Mark Mc Mahon and Contributors
Author-email: pywinauto-users@lists.sourceforge.net
License: BSD 3-clause
Keywords: windows gui automation GuiAuto testing test desktop mouse keyboard
Platform: win32
Classifier: Development Status :: 5 - Production/Stable
Classifier: Environment :: Console
Classifier: Intended Audience :: Developers
Classifier: License :: OSI Approved :: BSD License
Classifier: Operating System :: Microsoft :: Windows
Classifier: Programming Language :: Python
Classifier: Programming Language :: Python :: 2.7
Classifier: Programming Language :: Python :: 3.5
Classifier: Programming Language :: Python :: 3.6
Classifier: Programming Language :: Python :: 3.7
Classifier: Programming Language :: Python :: Implementation :: CPython
Classifier: Topic :: Software Development :: Libraries :: Python Modules
Classifier: Topic :: Software Development :: Testing
Classifier: Topic :: Software Development :: User Interfaces
Classifier: Topic :: Software Development :: Quality Assurance
